<?xml version="1.0"?>
<TriggernometryExport Version="1">
  <ExportedFolder Id="f1c24e2b-2ca9-47a4-ac6c-0324f42437a7" Name="Shaun's Triggers" Enabled="true">

    <Folders>

      <Folder Id="675948a6-abdf-47ed-8e26-4bd56d841871" Name="O3S" Enabled="true">
        <Folders />
        <Triggers>
          <Trigger Enabled="true" Source="FFXIVNetwork" Name="Halicarnassus - the Queen's Waltz - Tile" Id="37231cc7-9fff-4d71-8e3c-4fdcd3fafdbe" RegularExpression="^20\|[^|]*\|[^|]*\|[^|]*\|230E\|">
            <Actions>
              <Action OrderNumber="1" UseTTSTextExpression="Tile Spread" ActionType="UseTTS">
                <Condition Enabled="false" Grouping="Or" />
              </Action>
            </Actions>
            <Condition Enabled="false" Grouping="Or" />
          </Trigger>
          <Trigger Enabled="true" Source="FFXIVNetwork" Name="Halicarnassus - the Queen's Waltz - Protean" Id="2f69948d-336a-4cd8-92a1-e6f9602f6d47" RegularExpression="^20\|[^|]*\|[^|]*\|[^|]*\|2306\|">
            <Actions>
              <Action OrderNumber="1" UseTTSTextExpression="Boss Relative Spread" ActionType="UseTTS">
                <Condition Enabled="false" Grouping="Or" />
              </Action>
            </Actions>
            <Condition Enabled="false" Grouping="Or" />
          </Trigger>
          <Trigger Enabled="true" Source="FFXIVNetwork" Name="Halicarnassus - the Queen's Waltz - Tether" Id="770bba6c-893f-4d89-ab7f-733dd4a1aba8" RegularExpression="^20\|[^|]*\|[^|]*\|[^|]*\|2308\|">
            <Actions>
              <Action OrderNumber="1" UseTTSTextExpression="Go Mid" ActionType="UseTTS">
                <Condition Enabled="false" Grouping="Or" />
              </Action>
            </Actions>
            <Condition Enabled="false" Grouping="Or" />
          </Trigger>
          <Trigger Enabled="true" Source="FFXIVNetwork" Name=" Halicarnassus - the Queen's Waltz - Blue Tile" Id="2e59c687-825c-493d-80f7-85cfdd6e3c47" RegularExpression="^20\|[^|]*\|[^|]*\|[^|]*\|230A\|">
            <Actions>
              <Action OrderNumber="1" UseTTSTextExpression="Blue Tile" ActionType="UseTTS">
                <Condition Enabled="false" Grouping="Or" />
              </Action>
            </Actions>
            <Condition Enabled="false" Grouping="Or" />
          </Trigger>
        </Triggers>
      </Folder>



      <!-- Manual New Folder Goes Here -->

      
    </Folders>


    <!--Wipe Trigger-->

    <Triggers>
      <Trigger Enabled="true" Source="FFXIVNetwork" Name="Wipe" Id="041643aa-865a-48c8-88f6-20f05576b6bc" RegularExpression="^(01|33\|[^|]*\|[^|]*\|400000(?&gt;03|0F)\|)">
        <Actions>
          <Action OrderNumber="1" ActionType="Repository" ExecutionDelayExpression="500">
            <Condition Enabled="false" Grouping="Or" />
          </Action>
        </Actions>
        <Condition Enabled="false" Grouping="Or" />
        <Conditions />
      </Trigger>
    </Triggers>








  </ExportedFolder>
</TriggernometryExport>
